kormos/__init__.py
kormos/models.py
kormos/optimizers.py
kormos/utils/__init__.py
kormos/utils/cache.py
tests/__init__.py
tests/kormos/__init__.py
tests/kormos/test_models.py
tests/kormos/test_optimizers.py
tests/kormos/utils/__init__.py
tests/kormos/utils/test_cache.py
kormos-0.1.4.dist-info/LICENSE
kormos-0.1.4.dist-info/METADATA
kormos-0.1.4.dist-info/WHEEL
kormos-0.1.4.dist-info/top_level.txt
kormos-0.1.4.dist-info/RECORD
