Metadata-Version: 2.1
Name: kormos
Version: 0.1.4
Summary: An interface to scipy.optimize.minimize for training Keras models with batch optimization algorithms like L-BFGS.
Home-page: https://github.com/mbhynes/kormos
Author: Michael B Hynes
Author-email: mike.hynes.rhymes@gmail.com
Classifier: Programming Language :: Python :: 3
Classifier: License :: OSI Approved :: MIT License
Classifier: Operating System :: OS Independent
Classifier: Topic :: Scientific/Engineering :: Information Analysis
Requires-Python: >=3
License-File: LICENSE
Requires-Dist: tensorflow (>=2)
Requires-Dist: numpy
Requires-Dist: scipy
